flask_MailboxValidator/SingleValidation.py
flask_MailboxValidator/__init__.py
test/__init__.py
test/test_mbv.py
flask_MailboxValidator-1.3.0.dist-info/LICENSE.txt
flask_MailboxValidator-1.3.0.dist-info/METADATA
flask_MailboxValidator-1.3.0.dist-info/WHEEL
flask_MailboxValidator-1.3.0.dist-info/top_level.txt
flask_MailboxValidator-1.3.0.dist-info/RECORD
