Metadata-Version: 2.1
Name: flask-MailboxValidator
Version: 1.3.0
Summary: Email verification module for Flask using MailboxValidator API. It validates if the email is valid, from a free provider, contains high-risk keywords, whether it's a catch-all address and so much more.
Home-page: https://github.com/MailboxValidator/Flask_MailboxValidator
Author: MailboxValidator.com
Author-email: support@mailboxvalidator.com
Classifier: Development Status :: 5 - Production/Stable
Classifier: Intended Audience :: Developers
Classifier: Topic :: Software Development :: Libraries :: Python Modules
Classifier: Programming Language :: Python :: 2.7
Classifier: Programming Language :: Python :: 3
Classifier: License :: OSI Approved :: MIT License
Classifier: Operating System :: OS Independent
License-File: LICENSE.txt
Requires-Dist: Flask>=3.0.0
Requires-Dist: Flask-WTF>=1.0.0
Requires-Dist: WTForms>=3.0.0
Provides-Extra: tests
Requires-Dist: nose2; extra == "tests"
Provides-Extra: docs
Requires-Dist: sphinx>=1.8.1; extra == "docs"
Requires-Dist: Pallets-Sphinx-Themes; extra == "docs"
